[{"user":"joJo","objName":"objD","SDate":"2021-05-05","SHour":5,"EDate":"2021-05-28","EHour":10},{"user":"joJo","objName":"objD","SDate":"2021-05-05","SHour":5,"EDate":"2021-05-28","EHour":10},{"user":"joJo","objName":"objB","SDate":"2021-04-29","SHour":2,"EDate":"2021-05-22","EHour":8},{"user":"joJo","objName":"objB","SDate":"2021-05-12","SHour":5,"EDate":"2021-05-21","EHour":10},{"user":"joJo","objName":"objB","SDate":"2021-05-12","SHour":0,"EDate":"2021-05-21","EHour":10},{"user":"joJo","objName":"objB","SDate":"2021-05-12","SHour":3,"EDate":"2021-05-21","EHour":18},{"user":"joJo","objName":"objB","SDate":"2021-05-12","SHour":2,"EDate":"2021-05-21","EHour":13},{"user":"joJo","objName":"objB","SDate":"2021-05-12","SHour":1,"EDate":"2021-05-21","EHour":14},{"user":"joJo","objName":"objB","SDate":"2021-05-12","SHour":0,"EDate":"2021-05-12","EHour":15},{"user":"joJo","objName":"objB","SDate":"2021-05-05","SHour":3,"EDate":"2021-05-22","EHour":7},{"user":"joJo","objName":"objB","SDate":"2021-05-21","SHour":16,"EDate":"2021-05-22","EHour":16},{"user":"joJo","objName":"objA","SDate":"2021-05-18","SHour":0,"EDate":"2021-05-20","EHour":0}]